ibearychat/__init__.py
ibearychat/incoming.py
ibearychat-0.1.0.dist-info/LICENSE
ibearychat-0.1.0.dist-info/METADATA
ibearychat-0.1.0.dist-info/WHEEL
ibearychat-0.1.0.dist-info/top_level.txt
ibearychat-0.1.0.dist-info/RECORD
