Metadata-Version: 2.1
Name: ibearychat
Version: 0.1.0
Summary: Bearychat tools.
Home-page: https://pypi.org/project/ibearychat/
Author: teachmyself
Author-email: teachmyself@126.com
License: MIT
Keywords: ibearychat,bearychat,incoming
Platform: UNKNOWN
Classifier: Development Status :: 5 - Production/Stable
Classifier: Operating System :: OS Independent
Classifier: Intended Audience :: Developers
Classifier: License :: OSI Approved :: MIT License
Classifier: Programming Language :: Python :: 2.7
Classifier: Programming Language :: Python :: 3.4
Requires-Dist: requests
